Workbook

Sheet Inventario
A1: Código | B1: Prenda | C1: Categoría | D1: Talla | E1: Stock inicial | F1: Precio | G1: Costo unitario | H1: Calidad | I1: Foto | J1: Entregadas | K1: Pendientes | L1: Disponibles | M1: Alerta
A2: P-VN | B2: Vestido negro línea dorada | C2: Vestidos | D2: S | E2: 3 | F2: 89000 | G2: 42000 | H2: Crepé elástico con forro interior y línea dorada. Lavar a mano. | J2: =COUNTIFS(Pedidos!$E:$E,$B2,Pedidos!$F:$F,$D2,Pedidos!$I:$I,"Entregado") -> 2 | K2: =COUNTIFS(Pedidos!$E:$E,$B2,Pedidos!$F:$F,$D2,Pedidos!$I:$I,"Pendiente") -> 0 | L2: =E2-J2-K2 -> 1 | M2: =IF(L2<=0,"Reponer",IF(L2<=1,"Bajo","Ok")) -> Bajo
A3: P-VN | B3: Vestido negro línea dorada | C3: Vestidos | D3: M | E3: 3 | F3: 89000 | G3: 42000 | H3: Crepé elástico con forro interior y línea dorada. Lavar a mano. | J3: =COUNTIFS(Pedidos!$E:$E,$B3,Pedidos!$F:$F,$D3,Pedidos!$I:$I,"Entregado") -> 2 | K3: =COUNTIFS(Pedidos!$E:$E,$B3,Pedidos!$F:$F,$D3,Pedidos!$I:$I,"Pendiente") -> 0 | L3: =E3-J3-K3 -> 1 | M3: =IF(L3<=0,"Reponer",IF(L3<=1,"Bajo","Ok")) -> Bajo
A4: P-VN | B4: Vestido negro línea dorada | C4: Vestidos | D4: L | E4: 2 | F4: 89000 | G4: 42000 | H4: Crepé elástico con forro interior y línea dorada. Lavar a mano. | J4: =COUNTIFS(Pedidos!$E:$E,$B4,Pedidos!$F:$F,$D4,Pedidos!$I:$I,"Entregado") -> 1 | K4: =COUNTIFS(Pedidos!$E:$E,$B4,Pedidos!$F:$F,$D4,Pedidos!$I:$I,"Pendiente") -> 0 | L4: =E4-J4-K4 -> 1 | M4: =IF(L4<=0,"Reponer",IF(L4<=1,"Bajo","Ok")) -> Bajo
A5: P-VT | B5: Vestido midi terracota | C5: Vestidos | D5: S | E5: 2 | F5: 95000 | G5: 45000 | H5: Viscosa fluida, largo midi, cierre invisible. Lavar en frío. | J5: =COUNTIFS(Pedidos!$E:$E,$B5,Pedidos!$F:$F,$D5,Pedidos!$I:$I,"Entregado") -> 1 | K5: =COUNTIFS(Pedidos!$E:$E,$B5,Pedidos!$F:$F,$D5,Pedidos!$I:$I,"Pendiente") -> 0 | L5: =E5-J5-K5 -> 1 | M5: =IF(L5<=0,"Reponer",IF(L5<=1,"Bajo","Ok")) -> Bajo
A6: P-VT | B6: Vestido midi terracota | C6: Vestidos | D6: M | E6: 2 | F6: 95000 | G6: 45000 | H6: Viscosa fluida, largo midi, cierre invisible. Lavar en frío. | J6: =COUNTIFS(Pedidos!$E:$E,$B6,Pedidos!$F:$F,$D6,Pedidos!$I:$I,"Entregado") -> 2 | K6: =COUNTIFS(Pedidos!$E:$E,$B6,Pedidos!$F:$F,$D6,Pedidos!$I:$I,"Pendiente") -> 0 | L6: =E6-J6-K6 -> 0 | M6: =IF(L6<=0,"Reponer",IF(L6<=1,"Bajo","Ok")) -> Reponer
A7: P-BS | B7: Blusa satín champagne | C7: Blusas | D7: S | E7: 4 | F7: 45000 | G7: 18000 | H7: Satín liviano con cuello en V. Planchar a baja temperatura. | J7: =COUNTIFS(Pedidos!$E:$E,$B7,Pedidos!$F:$F,$D7,Pedidos!$I:$I,"Entregado") -> 3 | K7: =COUNTIFS(Pedidos!$E:$E,$B7,Pedidos!$F:$F,$D7,Pedidos!$I:$I,"Pendiente") -> 0 | L7: =E7-J7-K7 -> 1 | M7: =IF(L7<=0,"Reponer",IF(L7<=1,"Bajo","Ok")) -> Bajo
A8: P-BS | B8: Blusa satín champagne | C8: Blusas | D8: M | E8: 3 | F8: 45000 | G8: 18000 | H8: Satín liviano con cuello en V. Planchar a baja temperatura. | J8: =COUNTIFS(Pedidos!$E:$E,$B8,Pedidos!$F:$F,$D8,Pedidos!$I:$I,"Entregado") -> 2 | K8: =COUNTIFS(Pedidos!$E:$E,$B8,Pedidos!$F:$F,$D8,Pedidos!$I:$I,"Pendiente") -> 0 | L8: =E8-J8-K8 -> 1 | M8: =IF(L8<=0,"Reponer",IF(L8<=1,"Bajo","Ok")) -> Bajo
A9: P-BS | B9: Blusa satín champagne | C9: Blusas | D9: L | E9: 0 | F9: 45000 | G9: 18000 | H9: Satín liviano con cuello en V. Planchar a baja temperatura. | J9: =COUNTIFS(Pedidos!$E:$E,$B9,Pedidos!$F:$F,$D9,Pedidos!$I:$I,"Entregado") -> 0 | K9: =COUNTIFS(Pedidos!$E:$E,$B9,Pedidos!$F:$F,$D9,Pedidos!$I:$I,"Pendiente") -> 0 | L9: =E9-J9-K9 -> 0 | M9: =IF(L9<=0,"Reponer",IF(L9<=1,"Bajo","Ok")) -> Reponer
A10: P-CL | B10: Camisa lino blanco | C10: Camisas | D10: M | E10: 3 | F10: 52000 | G10: 21000 | H10: Lino con algodón, corte regular. Se arruga: es parte del estilo. | J10: =COUNTIFS(Pedidos!$E:$E,$B10,Pedidos!$F:$F,$D10,Pedidos!$I:$I,"Entregado") -> 1 | K10: =COUNTIFS(Pedidos!$E:$E,$B10,Pedidos!$F:$F,$D10,Pedidos!$I:$I,"Pendiente") -> 0 | L10: =E10-J10-K10 -> 2 | M10: =IF(L10<=0,"Reponer",IF(L10<=1,"Bajo","Ok")) -> Ok
A11: P-CL | B11: Camisa lino blanco | C11: Camisas | D11: L | E11: 2 | F11: 52000 | G11: 21000 | H11: Lino con algodón, corte regular. Se arruga: es parte del estilo. | J11: =COUNTIFS(Pedidos!$E:$E,$B11,Pedidos!$F:$F,$D11,Pedidos!$I:$I,"Entregado") -> 2 | K11: =COUNTIFS(Pedidos!$E:$E,$B11,Pedidos!$F:$F,$D11,Pedidos!$I:$I,"Pendiente") -> 0 | L11: =E11-J11-K11 -> 0 | M11: =IF(L11<=0,"Reponer",IF(L11<=1,"Bajo","Ok")) -> Reponer
A12: P-BN | B12: Bolso estructurado negro | C12: Accesorios | D12: Única | E12: 3 | F12: 72000 | G12: 30000 | H12: Material sintético estructurado, forro interior y herraje dorado. | J12: =COUNTIFS(Pedidos!$E:$E,$B12,Pedidos!$F:$F,$D12,Pedidos!$I:$I,"Entregado") -> 2 | K12: =COUNTIFS(Pedidos!$E:$E,$B12,Pedidos!$F:$F,$D12,Pedidos!$I:$I,"Pendiente") -> 0 | L12: =E12-J12-K12 -> 1 | M12: =IF(L12<=0,"Reponer",IF(L12<=1,"Bajo","Ok")) -> Bajo
A13: P-AD | B13: Aretes dorados par | C13: Accesorios | D13: Única | E13: 6 | F13: 28000 | G13: 8000 | H13: Baño dorado, par. Evitar el contacto con agua y perfume. | J13: =COUNTIFS(Pedidos!$E:$E,$B13,Pedidos!$F:$F,$D13,Pedidos!$I:$I,"Entregado") -> 2 | K13: =COUNTIFS(Pedidos!$E:$E,$B13,Pedidos!$F:$F,$D13,Pedidos!$I:$I,"Pendiente") -> 0 | L13: =E13-J13-K13 -> 4 | M13: =IF(L13<=0,"Reponer",IF(L13<=1,"Bajo","Ok")) -> Ok
... A15: P-CI | B15: Cinturón hebilla dorada | C15: Accesorios | D15: M | E15: 3 | F15: 38000 | G15: 12000 | H15: Correa negra con hebilla dorada. Ajustable. | J15: =COUNTIFS(Pedidos!$E:$E,$B15,Pedidos!$F:$F,$D15,Pedidos!$I:$I,"Entregado") -> 1 | K15: =COUNTIFS(Pedidos!$E:$E,$B15,Pedidos!$F:$F,$D15,Pedidos!$I:$I,"Pendiente") -> 0 | L15: =E15-J15-K15 -> 2 | M15: =IF(L15<=0,"Reponer",IF(L15<=1,"Bajo","Ok")) -> Ok

Sheet Pedidos
A1: ID | B1: Fecha | C1: ClienteID | D1: Categoría | E1: Prenda | F1: Talla | G1: Precio | H1: Canal | I1: Estado | J1: Registró
A2: V001 | B2: 46266 | C2: C01 | D2: Vestidos | E2: Vestido negro línea dorada | F2: M | G2: 89000 | H2: Instagram | I2: Entregado | J2: Xairy
A3: V002 | B3: 46266 | C3: C02 | D3: Blusas | E3: Blusa satín champagne | F3: S | G3: 45000 | H3: WhatsApp | I3: Entregado | J3: Angelly
A4: V003 | B4: 46267 | C4: C03 | D4: Accesorios | E4: Bolso estructurado negro | F4: Única | G4: 72000 | H4: WhatsApp | I4: Entregado | J4: Claudia
A5: V004 | B5: 46267 | C5: C04 | D5: Camisas | E5: Camisa lino blanco | F5: L | G5: 52000 | H5: Instagram | I5: Entregado | J5: Xairy
A6: V005 | B6: 46268 | C6: C05 | D6: Vestidos | E6: Vestido negro línea dorada | F6: S | G6: 89000 | H6: WhatsApp | I6: Entregado | J6: Angelly
A7: V006 | B7: 46268 | C7: C06 | D7: Blusas | E7: Blusa satín champagne | F7: M | G7: 45000 | H7: Presencial | I7: Entregado | J7: Xairy
A8: V007 | B8: 46269 | C8: C07 | D8: Camisas | E8: Camisa lino blanco | F8: M | G8: 52000 | H8: Instagram | I8: Cancelado | J8: Xairy
A9: V008 | B9: 46269 | C9: C08 | D9: Vestidos | E9: Vestido midi terracota | F9: M | G9: 95000 | H9: WhatsApp | I9: Entregado | J9: Angelly
A10: V009 | B10: 46270 | C10: C09 | D10: Accesorios | E10: Aretes dorados par | F10: Única | G10: 28000 | H10: WhatsApp | I10: Entregado | J10: Claudia
A11: V010 | B11: 46270 | C11: C10 | D11: Camisas | E11: Camisa lino blanco | F11: L | G11: 52000 | H11: Instagram | I11: Entregado | J11: Xairy
A12: V011 | B12: 46273 | C12: C11 | D12: Blusas | E12: Blusa satín champagne | F12: S | G12: 45000 | H12: WhatsApp | I12: Entregado | J12: Angelly
A13: V012 | B13: 46273 | C13: C12 | D13: Vestidos | E13: Vestido negro línea dorada | F13: L | G13: 89000 | H13: Presencial | I13: Entregado | J13: Xairy
... A25: V024 | B25: 46284 | C25: C05 | D25: Accesorios | E25: Cinturón hebilla dorada | F25: S | G25: 38000 | H25: WhatsApp | I25: Entregado | J25: Claudia

Sheet Clientes
A1: ID | B1: Edad | C1: Sexo | D1: Canal de contacto | E1: Preguntó precio antes | F1: Preguntó talla o calidad | G1: Frecuencia que dice comprar
A2: C01 | B2: 22 | C2: Mujer | D2: Instagram | E2: Sí | F2: Sí | G2: 1 vez al mes
A3: C02 | B3: 19 | C3: Mujer | D3: WhatsApp | E3: Sí | F3: Sí | G3: 2 veces al mes
A4: C03 | B4: 28 | C4: Mujer | D4: WhatsApp | E4: Sí | F4: No | G4: Cada dos meses
A5: C04 | B5: 24 | C5: Hombre | D5: Instagram | E5: No | F5: Sí | G5: 1 vez al mes
A6: C05 | B6: 17 | C6: Mujer | D6: WhatsApp | E6: Sí | F6: Sí | G6: 1 vez al mes
A7: C06 | B7: 36 | C7: Mujer | D7: Presencial | E7: Sí | F7: Sí | G7: Cada dos meses
A8: C07 | B8: 21 | C8: Hombre | D8: Instagram | E8: Sí | F8: No | G8: Casi no compra
A9: C08 | B9: 20 | C9: Mujer | D9: WhatsApp | E9: Sí | F9: Sí | G9: 2 veces al mes
A10: C09 | B10: 31 | C10: Mujer | D10: WhatsApp | E10: Sí | F10: Sí | G10: 1 vez al mes
A11: C10 | B11: 27 | C11: Hombre | D11: Instagram | E11: No | F11: No | G11: 1 vez al mes
A12: C11 | B12: 18 | C12: Mujer | D12: WhatsApp | E12: Sí | F12: Sí | G12: 2 veces al mes
A13: C12 | B13: 41 | C13: Mujer | D13: Presencial | E13: Sí | F13: Sí | G13: Cada dos meses
... A17: C16 | B17: 40 | C17: Mujer | D17: Presencial | E17: Sí | F17: Sí | G17: Pedido grupal

Sheet Directorio
A1: ID | B1: Nombre | C1: Contacto
A2: C01 | B2: Laura Méndez
A3: C02 | B3: Karol Pinto
A4: C03 | B4: Andrea Luz
A5: C04 | B5: Miguel Ángel R.
A6: C05 | B6: Valentina S.
A7: C06 | B7: Prof. Elena D.
A8: C07 | B8: Juan Diego P.
A9: C08 | B9: Sara Bolívar
A10: C09 | B10: Camila Ortiz
A11: C10 | B11: Diego Ferrer
A12: C11 | B12: Natalia Gil
A13: C12 | B13: Rosa Jiménez
... A17: C16 | B17: Coordinación IE

Sheet Instrucciones
A1: Cómo funciona esta hoja
A2: Es la base de datos de CABAX. El catálogo y el tablero del sitio web la leen cada vez que se abren.
A4: Qué pestañas se publican en la web (Archivo > Compartir > Publicar en la web > elegir la pestaña > CSV)
A5: • Inventario, Pedidos y Clientes: SÍ se publican. Aquí no deben ir nombres ni teléfonos.
A6: • Directorio: NO se publica nunca. Es la única pestaña con nombres de clientes (ID → nombre).
A7: • Instrucciones: NO se publica.
A9: Cómo se registra una venta
A10: 1. El cliente pide por WhatsApp (desde el catálogo o por chat).
A11: 2. En el tablero, pestaña “Registrar un pedido”, pega el mensaje. El asistente prepara las filas.
A12: 3. Pega la fila en Pedidos (estado Pendiente). Si el cliente es nuevo, pega también Clientes y Directorio.
A13: 4. Cuando se entrega, cambia el estado a Entregado. Si se cancela, Cancelado. Si no había la talla, No había talla.
A14: 5. El inventario se actualiza solo: Disponibles = Stock inicial − Entregadas − Pendientes.
... A26: La columna Foto es opcional: escribe el nombre de un archivo guardado en la carpeta fotos del sitio (por ejemplo fotos/vestido-negro.jpg).
